jupyterlab_novnc/__init__.py
jupyterlab_novnc/_version.py
jupyterlab_novnc/handlers.py
jupyterlab_novnc/labextension/package.json
jupyterlab_novnc/labextension/schemas/jupyterlab-novnc/package.json.orig
jupyterlab_novnc/labextension/schemas/jupyterlab-novnc/plugin.json
jupyterlab_novnc/labextension/static/480.7a43441b238c340b14be.js
jupyterlab_novnc/labextension/static/534.c71f6562e5368aa52e29.js
jupyterlab_novnc/labextension/static/remoteEntry.9c1e9be356ae175fd5ec.js
jupyterlab_novnc/labextension/static/style.js
jupyterlab_novnc/novnc/.eslintignore
jupyterlab_novnc/novnc/.eslintrc
jupyterlab_novnc/novnc/.gitignore
jupyterlab_novnc/novnc/.gitmodules
jupyterlab_novnc/novnc/AUTHORS
jupyterlab_novnc/novnc/LICENSE.txt
jupyterlab_novnc/novnc/README.md
jupyterlab_novnc/novnc/karma.conf.js
jupyterlab_novnc/novnc/package.json
jupyterlab_novnc/novnc/vnc.html
jupyterlab_novnc/novnc/vnc_lite.html
jupyterlab_novnc/novnc/.github/ISSUE_TEMPLATE/bug_report.md
jupyterlab_novnc/novnc/.github/ISSUE_TEMPLATE/feature_request.md
jupyterlab_novnc/novnc/.github/workflows/deploy.yml
jupyterlab_novnc/novnc/.github/workflows/lint.yml
jupyterlab_novnc/novnc/.github/workflows/test.yml
jupyterlab_novnc/novnc/app/error-handler.js
jupyterlab_novnc/novnc/app/localization.js
jupyterlab_novnc/novnc/app/ui.js
jupyterlab_novnc/novnc/app/webutil.js
jupyterlab_novnc/novnc/app/images/alt.svg
jupyterlab_novnc/novnc/app/images/clipboard.svg
jupyterlab_novnc/novnc/app/images/connect.svg
jupyterlab_novnc/novnc/app/images/ctrl.svg
jupyterlab_novnc/novnc/app/images/ctrlaltdel.svg
jupyterlab_novnc/novnc/app/images/disconnect.svg
jupyterlab_novnc/novnc/app/images/drag.svg
jupyterlab_novnc/novnc/app/images/error.svg
jupyterlab_novnc/novnc/app/images/esc.svg
jupyterlab_novnc/novnc/app/images/expander.svg
jupyterlab_novnc/novnc/app/images/fullscreen.svg
jupyterlab_novnc/novnc/app/images/handle.svg
jupyterlab_novnc/novnc/app/images/handle_bg.svg
jupyterlab_novnc/novnc/app/images/info.svg
jupyterlab_novnc-0.2.1.dist-info/LICENSE
jupyterlab_novnc-0.2.1.dist-info/METADATA
jupyterlab_novnc-0.2.1.dist-info/WHEEL
jupyterlab_novnc-0.2.1.dist-info/top_level.txt
jupyterlab_novnc-0.2.1.dist-info/RECORD
