Metadata-Version: 2.1
Name: jupyterlab-novnc
Version: 0.2.1
Summary: novnc for jlab
Home-page: https://github.com/robostack/jupyterlab-novnc
Author: Wolf Vollprecht
Author-email: w.vollprecht@gmail.com
License: BSD-3-Clause
Keywords: Jupyter,JupyterLab,JupyterLab3
Platform: Linux
Platform: Mac OS X
Platform: Windows
Classifier: License :: OSI Approved :: BSD License
Classifier: Programming Language :: Python
Classifier: Programming Language :: Python :: 3
Classifier: Programming Language :: Python :: 3.6
Classifier: Programming Language :: Python :: 3.7
Classifier: Programming Language :: Python :: 3.8
Classifier: Programming Language :: Python :: 3.9
Classifier: Framework :: Jupyter
Requires-Python: >=3.6
License-File: LICENSE
Requires-Dist: jupyterlab (~=3.0)
Requires-Dist: jupyter-packaging (<2,~=0.9)
